ysb_common/DateTools.py
ysb_common/Nsrlxdm.py
ysb_common/OssTool.py
ysb_common/YsbException.py
ysb_common/__init__.py
ysb_common/configures/__init__.py
ysb_common/configures/log.py
ysb_common/configures/params.py
ysb_common/configures/redis.py
ysb_common/constants/__init__.py
ysb_common/constants/constant.py
ysb_common/constants/nsrlx.py
ysb_common/constants/sbbzl.py
ysb_common/constants/yzpzzl.py
ysb_common/constants/zspm.py
ysb_common/constants/zsxm.py
ysb_common/exception/YsbException.py
ysb_common/exception/__init__.py
ysb_common/queneapi/__init__.py
ysb_common/queneapi/queueApi.py
ysb_common/tools/__init__.py
ysb_common/tools/dataTool.py
ysb_common/tools/dateTools.py
ysb_common/tools/ossTool.py
ysb_common/tools/redisTools.py
ysb_common/tools/requestTools.py
ysb_common/tools/seleniumTool.py
ysb_common-2.1.1.dist-info/LICENSE
ysb_common-2.1.1.dist-info/METADATA
ysb_common-2.1.1.dist-info/WHEEL
ysb_common-2.1.1.dist-info/top_level.txt
ysb_common-2.1.1.dist-info/RECORD
