Metadata-Version: 2.1
Name: ysb-common
Version: 2.1.1
Summary: ysb common
Home-page: https://markdown.felinae.net
Author: ysb
Author-email: 497257761@qq.com
License: UNKNOWN
Keywords: django markdown editor editormd
Platform: UNKNOWN
Classifier: Programming Language :: Python
Classifier: Development Status :: 4 - Beta
Classifier: Operating System :: OS Independent
Classifier: License :: OSI Approved :: Apache Software License
Requires-Dist: oss2
